django_serializer_json
