Metadata-Version: 1.0
Name: django-serializer-json
Version: 0.9
Summary: Simple json serializer for Django FW
Home-page: UNKNOWN
Author: Alex Gonchar
Author-email: UNKNOWN
License: UNKNOWN
Platform: UNKNOWN
